mapdemo/__init__.py
mapdemo/common.py
mapdemo/foliummap.py
mapdemo/mapdemo.py
mapdemo/utils.py
mapdemo-0.0.6.dist-info/licenses/LICENSE
mapdemo-0.0.6.dist-info/METADATA
mapdemo-0.0.6.dist-info/WHEEL
mapdemo-0.0.6.dist-info/entry_points.txt
mapdemo-0.0.6.dist-info/top_level.txt
mapdemo-0.0.6.dist-info/RECORD
