Metadata-Version: 2.4
Name: mapdemo
Version: 0.0.6
Summary: A python package used for web map application
Author-email: Atul Bhardwaj <atulmncfc@gmail.com>
License: MIT License
Project-URL: Homepage, https://github.com/gisatb/mapdemo
Keywords: mapdemo
Classifier: Intended Audience :: Developers
Classifier: License :: OSI Approved :: MIT License
Classifier: Natural Language :: English
Classifier: Programming Language :: Python :: 3.8
Classifier: Programming Language :: Python :: 3.9
Classifier: Programming Language :: Python :: 3.10
Classifier: Programming Language :: Python :: 3.11
Classifier: Programming Language :: Python :: 3.12
Requires-Python: >=3.8
License-File: LICENSE
Requires-Dist: numpy
Requires-Dist: ipyleaflet
Requires-Dist: localtileserver
Requires-Dist: shapely
Requires-Dist: pandas
Requires-Dist: ipywidgets
Requires-Dist: folium
Provides-Extra: all
Requires-Dist: mapdemo[extra]; extra == "all"
Provides-Extra: extra
Requires-Dist: pandas; extra == "extra"
Dynamic: license-file
